sphinxcontrib_d2lang-0.0.5-py3.11-nspkg.pth
sphinxcontrib/d2lang/__init__.py
sphinxcontrib/d2lang/d2lang.py
sphinxcontrib_d2lang-0.0.5.dist-info/METADATA
sphinxcontrib_d2lang-0.0.5.dist-info/WHEEL
sphinxcontrib_d2lang-0.0.5.dist-info/namespace_packages.txt
sphinxcontrib_d2lang-0.0.5.dist-info/top_level.txt
sphinxcontrib_d2lang-0.0.5.dist-info/RECORD
