Metadata-Version: 2.1
Name: sphinxcontrib-d2lang
Version: 0.0.5
Summary: an extension for sphinx to render d2lang diagrams in sphinx documents
Home-page: https://git.0w.tf/Milka64/sphinx-d2lang/
Author: Milka64
Author-email: Milka64 <michael.ricart@0w.tf>
Project-URL: Homepage, https://git.0w.tf/Milka64/sphinx-d2lang/
Project-URL: Issues, https://git.0w.tf/Milka64/sphinx-d2lang/issues
Classifier: Programming Language :: Python :: 3
Classifier: License :: OSI Approved :: MIT License
Classifier: Operating System :: OS Independent
Requires-Python: >=3.8
Requires-Dist: docutils ==0.20.1
Requires-Dist: setuptools ==67.7.2
Requires-Dist: Sphinx ==7.2.6
Requires-Dist: wheel ==0.42.0
